aiagents4pharma/__init__.py
aiagents4pharma/talk2aiagents4pharma/.dockerignore
aiagents4pharma/talk2aiagents4pharma/Dockerfile
aiagents4pharma/talk2aiagents4pharma/README.md
aiagents4pharma/talk2aiagents4pharma/__init__.py
aiagents4pharma/talk2aiagents4pharma/install.md
aiagents4pharma/talk2aiagents4pharma/agents/__init__.py
aiagents4pharma/talk2aiagents4pharma/agents/main_agent.py
aiagents4pharma/talk2aiagents4pharma/configs/__init__.py
aiagents4pharma/talk2aiagents4pharma/configs/config.yaml
aiagents4pharma/talk2aiagents4pharma/configs/agents/__init__.py
aiagents4pharma/talk2aiagents4pharma/configs/agents/main_agent/default.yaml
aiagents4pharma/talk2aiagents4pharma/docker-compose/cpu/.env.example
aiagents4pharma/talk2aiagents4pharma/docker-compose/cpu/docker-compose.yml
aiagents4pharma/talk2aiagents4pharma/docker-compose/gpu/.env.example
aiagents4pharma/talk2aiagents4pharma/docker-compose/gpu/docker-compose.yml
aiagents4pharma/talk2aiagents4pharma/states/__init__.py
aiagents4pharma/talk2aiagents4pharma/states/state_talk2aiagents4pharma.py
aiagents4pharma/talk2aiagents4pharma/tests/__init__.py
aiagents4pharma/talk2aiagents4pharma/tests/test_main_agent.py
aiagents4pharma/talk2biomodels/.dockerignore
aiagents4pharma/talk2biomodels/Dockerfile
aiagents4pharma/talk2biomodels/README.md
aiagents4pharma/talk2biomodels/__init__.py
aiagents4pharma/talk2biomodels/install.md
aiagents4pharma/talk2biomodels/agents/__init__.py
aiagents4pharma/talk2biomodels/agents/t2b_agent.py
aiagents4pharma/talk2biomodels/api/__init__.py
aiagents4pharma/talk2biomodels/api/kegg.py
aiagents4pharma/talk2biomodels/api/ols.py
aiagents4pharma/talk2biomodels/api/uniprot.py
aiagents4pharma/talk2biomodels/configs/__init__.py
aiagents4pharma/talk2biomodels/configs/config.yaml
aiagents4pharma/talk2biomodels/configs/agents/__init__.py
aiagents4pharma/talk2biomodels/configs/agents/t2b_agent/__init__.py
aiagents4pharma/talk2biomodels/configs/agents/t2b_agent/default.yaml
aiagents4pharma_ansh-1.43.1.dist-info/METADATA
aiagents4pharma_ansh-1.43.1.dist-info/WHEEL
aiagents4pharma_ansh-1.43.1.dist-info/licenses/LICENSE
aiagents4pharma_ansh-1.43.1.dist-info/RECORD
